ngoto/__init__.py
ngoto/cogs/__init__.py
ngoto/cogs/basic.py
ngoto/cogs/chrome_passwords.py
ngoto/cogs/osint_framework.py
ngoto/cogs/pc_usage_monitor.py
ngoto/cogs/url.py
ngoto/cogs/wifi_passwords.py
ngoto/core/__init__.py
ngoto/core/decorators.py
ngoto/core/ngoto.py
ngoto/core/util/__init__.py
ngoto/core/util/interface.py
ngoto/core/util/logging.py
ngoto/core/util/node.py
ngoto/core/util/notify.py
ngoto/core/util/task_controller.py
ngoto/core/util/rich/__init__.py
ngoto/core/util/rich/__main__.py
ngoto/core/util/rich/_cell_widths.py
ngoto/core/util/rich/_emoji_codes.py
ngoto/core/util/rich/_emoji_replace.py
ngoto/core/util/rich/_export_format.py
ngoto/core/util/rich/_extension.py
ngoto/core/util/rich/_fileno.py
ngoto/core/util/rich/_inspect.py
ngoto/core/util/rich/_log_render.py
ngoto/core/util/rich/_loop.py
ngoto/core/util/rich/_null_file.py
ngoto/core/util/rich/_palettes.py
ngoto/core/util/rich/_pick.py
ngoto/core/util/rich/_ratio.py
ngoto/core/util/rich/_spinners.py
ngoto/core/util/rich/_stack.py
ngoto/core/util/rich/_timer.py
ngoto/core/util/rich/_win32_console.py
ngoto/core/util/rich/_windows.py
ngoto/core/util/rich/_windows_renderer.py
ngoto/core/util/rich/_wrap.py
ngoto/core/util/rich/abc.py
ngoto/core/util/rich/align.py
ngoto/core/util/rich/ansi.py
ngoto/core/util/rich/bar.py
ngoto/core/util/rich/box.py
ngoto/core/util/rich/cells.py
ngoto/core/util/rich/color.py
ngoto/core/util/rich/color_triplet.py
ngoto/core/util/rich/columns.py
ngoto/core/util/rich/console.py
ngoto/core/util/rich/constrain.py
ngoto/core/util/rich/containers.py
ngoto/core/util/rich/control.py
ngoto/core/util/rich/default_styles.py
ngoto/core/util/rich/diagnose.py
ngoto/core/util/rich/emoji.py
ngoto/core/util/rich/errors.py
ngoto/core/util/rich/file_proxy.py
ngoto/core/util/rich/filesize.py
ngoto/core/util/rich/highlighter.py
ngoto/core/util/rich/json.py
ngoto/core/util/rich/jupyter.py
ngoto/core/util/rich/layout.py
ngoto/core/util/rich/live.py
ngoto/core/util/rich/live_render.py
Ngoto-0.0.39.dist-info/METADATA
Ngoto-0.0.39.dist-info/WHEEL
Ngoto-0.0.39.dist-info/top_level.txt
Ngoto-0.0.39.dist-info/RECORD
